howitz/__init__.py
howitz/__main__.py
howitz/endpoints.py
howitz/error_handlers.py
howitz/utils.py
howitz/config/__init__.py
howitz/config/defaults.py
howitz/config/flask.py
howitz/config/howitz.py
howitz/config/log.py
howitz/config/models.py
howitz/config/utils.py
howitz/config/zino1.py
howitz/static/main.css
howitz/static/dist/main.css
howitz/templates/components/accordion/event-actions-buttons.html
howitz/templates/components/accordion/event-attributes.html
howitz/templates/components/accordion/event-details-content.html
howitz/templates/components/accordion/event-details.html
howitz/templates/components/accordion/event-messages-block.html
howitz/templates/components/accordion/event-messages.html
howitz/templates/components/accordion/update-state-btn.html
howitz/templates/components/feedback/spinner/spinner.html
howitz/templates/components/feedback/spinner/spinner.svg
howitz/templates/components/footer/footer-info.html
howitz/templates/components/footer/footer.html
howitz/templates/components/login/sign-in-form.html
howitz/templates/components/navbar/navbar.html
howitz/templates/components/navbar/user-dropdown-menu-expanded.html
howitz/templates/components/navbar/user-dropdown-menu-hidden.html
howitz/templates/components/navbar/user-menu-btn-expanded.html
howitz/templates/components/navbar/user-menu-btn.html
howitz/templates/components/popups/alerts/close-icon.svg
howitz/templates/components/popups/alerts/error/error-alert.html
howitz/templates/components/popups/alerts/error/error-icon.svg
howitz/templates/components/popups/alerts/error/maximize-icon.svg
howitz/templates/components/popups/alerts/error/minimize-icon.svg
howitz/templates/components/popups/bulk-update-menu/bulk-update-buttons.html
howitz/templates/components/popups/bulk-update-menu/bulk-update-menu.html
howitz/templates/components/popups/bulk-update-menu/bulk-update-progress.html
howitz/templates/components/popups/modals/table-operation-modal.html
howitz-0.1a3.dist-info/WHEEL
howitz-0.1a3.dist-info/METADATA
howitz-0.1a3.dist-info/RECORD
