Metadata-Version: 2.1
Name: howitz
Version: 0.1a3
Summary: blbl
Author-email: Hanne Moa <hanne.moa@sikt.no>, Ilona Podliashanyk <ilona.podliashanyk@sikt.no>
Requires-Python: >=3.8
Classifier: License :: OSI Approved :: Apache Software License
Requires-Dist: flask
Requires-Dist: flask-caching
Requires-Dist: flask_assets
Requires-Dist: flask-login
Requires-Dist: jinja2
Requires-Dist: zinolib>=1.3.0
Requires-Dist: werkzeug<3
Requires-Dist: pydantic
Requires-Dist: ruff ; extra == "dev"
Requires-Dist: pip-tools ; extra == "dev"
Requires-Dist: sphinx ; extra == "docs"
Provides-Extra: dev
Provides-Extra: docs
